{
  "stationCollection": [
    {
      "id": "0c1e6760-ec75-11eb-ab72-af455e89253c",
      "userid": "3ad52697-6d98-4d80-8273-084de55a86c0",
      "name": "Tramore",
      "latitude": 52.16,
      "longitude": -7.152,
      "latestWeather": {
        "tempFarenheit": "66.87",
        "beaufort": 1,
        "pressure": 1011,
        "temperature": 19.37,
        "code": 300,
        "compassDirection": "W",
        "windChill": "21.11",
        "conditions": "Cloudy",
        "minWindSpeed": 1,
        "maxWindSpeed": 3.5,
        "minTemp": 0.5,
        "maxTemp": 19.37,
        "minPressure": 1002,
        "maxPressure": 1011,
        "weatherIcon": "grey cloud",
        "tempTrend": "arrow up",
        "windTrend": "",
        "pressureTrend": "arrow up"
      },
      "readings": [
        {
          "id": "1ab60f80-ec75-11eb-ab72-af455e89253c",
          "code": 800,
          "temperature": 0.5,
          "windSpeed": 3.5,
          "pressure": 1002,
          "windDirection": 90,
          "date": "2021-04-25T07:20:42.138Z"
        },
        {
          "id": "250d9cf0-ec75-11eb-ab72-af455e89253c",
          "code": 600,
          "temperature": 6,
          "windSpeed": 2,
          "pressure": 1004,
          "windDirection": 96,
          "date": "2021-05-25T07:20:42.138Z"
        },
        {
          "id": "2e763680-ec75-11eb-ab72-af455e89253c",
          "code": 700,
          "temperature": 8,
          "windSpeed": 1,
          "pressure": 1005,
          "windDirection": 101,
          "date": "2021-06-25T07:20:42.138Z"
        },
        {
          "id": "00d39f80-029e-11ec-bc00-7d9363b06c70",
          "date": "2021-08-21T16:36:58.360Z",
          "code": 300,
          "temperature": 19.37,
          "windSpeed": 1.79,
          "pressure": 1011,
          "windDirection": 262
        },
        {
          "id": "84c10f40-0437-11ec-a06d-63bf3592f3af",
          "date": "2021-08-23T17:28:23.861Z",
          "code": 300,
          "temperature": 19.55,
          "windSpeed": 0.89,
          "pressure": 1029,
          "windDirection": 201
        }
      ]
    },
    {
      "id": "3d81af10-ec75-11eb-ab72-af455e89253c",
      "userid": "3ad52697-6d98-4d80-8273-084de55a86c0",
      "name": "Dunmore",
      "latitude": 52.149,
      "longitude": -6.994,
      "latestWeather": {
        "tempFarenheit": "66.79",
        "beaufort": 1,
        "pressure": 1030,
        "temperature": 19.33,
        "code": 300,
        "compassDirection": "S",
        "windChill": "20.97",
        "conditions": "Cloudy",
        "minWindSpeed": 1,
        "maxWindSpeed": 100,
        "minTemp": 0.5,
        "maxTemp": 19.33,
        "minPressure": 999,
        "maxPressure": 1030,
        "weatherIcon": "grey cloud",
        "tempTrend": "arrow up",
        "windTrend": "arrow down",
        "pressureTrend": "arrow up"
      },
      "readings": [
        {
          "id": "49c46ab0-ec75-11eb-ab72-af455e89253c",
          "code": 700,
          "temperature": 8,
          "windSpeed": 1,
          "pressure": 999,
          "windDirection": 98,
          "date": "2021-02-25T07:20:42.138Z"
        },
        {
          "id": "63e98830-ec75-11eb-ab72-af455e89253c",
          "code": 200,
          "temperature": 0.5,
          "windSpeed": 3.5,
          "pressure": 1000,
          "windDirection": 102,
          "date": "2021-03-25T07:20:42.138Z"
        },
        {
          "id": "3a81e420-ec97-11eb-bb82-995a4e8f3349",
          "code": 300,
          "temperature": 5,
          "windSpeed": 100,
          "pressure": 1000,
          "windDirection": 150,
          "date": "2021-01-25T07:20:42.138Z"
        },
        {
          "id": "b0948580-029c-11ec-9d3e-1f6ff4564d6a",
          "date": "2021-08-21T16:27:34.232Z",
          "code": 300,
          "temperature": 19.27,
          "windSpeed": 6.17,
          "pressure": 1012,
          "windDirection": 240
        },
        {
          "id": "793fa7d0-0437-11ec-a06d-63bf3592f3af",
          "date": "2021-08-23T17:28:04.557Z",
          "code": 300,
          "temperature": 19.33,
          "windSpeed": 2.06,
          "pressure": 1030,
          "windDirection": 180
        }
      ]
    }
  ]
}